greendeck_redis/__init__.py
greendeck_redis/src/redis/__init__.py
greendeck_redis/src/redis/redis.py
greendeck_redis-1.0.1.dist-info/LICENSE
greendeck_redis-1.0.1.dist-info/METADATA
greendeck_redis-1.0.1.dist-info/WHEEL
greendeck_redis-1.0.1.dist-info/top_level.txt
greendeck_redis-1.0.1.dist-info/RECORD
