Metadata-Version: 2.1
Name: greendeck-redis
Version: 1.0.1
Summary: Greendeck Redis Package
Home-page: https://github.com/yash6992
Author: yashvardhan srivastava
Author-email: yash@greendeck.com
License: UNKNOWN
Platform: UNKNOWN
Classifier: Programming Language :: Python :: 3
Classifier: License :: OSI Approved :: MIT License
Classifier: Operating System :: OS Independent
Requires-Dist: redis
